htbcli/__init__.py
htbcli/cli.py
htbcli/common_options.py
htbcli/output.py
htbcli/version.py
htbcli/box/__init__.py
htbcli/box/commands.py
htbcli/box/formatter.py
htbcli/box/lister.py
htbcli/box/power.py
htbcli/vpn/__init__.py
htbcli/vpn/commands.py
htbcli/vpn/htb.py
htbcli/vpn/nm.py
htbcli/vpn/util.py
PyHTBcli-0.0.7.dist-info/METADATA
PyHTBcli-0.0.7.dist-info/WHEEL
PyHTBcli-0.0.7.dist-info/entry_points.txt
PyHTBcli-0.0.7.dist-info/top_level.txt
PyHTBcli-0.0.7.dist-info/RECORD
