Metadata-Version: 2.1
Name: PyHTBcli
Version: 0.0.7
Summary: Command line interface for HackTheBox
Home-page: https://github.com/0xdf223/PyHTBcli
Author: 0xdf
Author-email: 0xdf.223@gmail.com
License: UNKNOWN
Platform: UNKNOWN
Requires-Python: >=3.8
Requires-Dist: click (>=8.0.4)
Requires-Dist: click-shell (>=2.1)
Requires-Dist: prettytable (>=3.1.1)
Requires-Dist: PyHackTheBox (>=0.5.4)
